MANIFEST.in
README.rst
setup.py
django_ideia_summernote.egg-info/PKG-INFO
django_ideia_summernote.egg-info/SOURCES.txt
django_ideia_summernote.egg-info/dependency_links.txt
django_ideia_summernote.egg-info/requires.txt
django_ideia_summernote.egg-info/top_level.txt
ideia_summernote/__init__.py
ideia_summernote/admin.py
ideia_summernote/apps.py
ideia_summernote/default.py
ideia_summernote/fields.py
ideia_summernote/ideia_forms.py
ideia_summernote/local_exceptions.py
ideia_summernote/models.py
ideia_summernote/tests.py
ideia_summernote/urls.py
ideia_summernote/views.py
ideia_summernote/widget.py
ideia_summernote/migrations/__init__.py
ideia_summernote/static/js/django-jquery-adapter.js
ideia_summernote/static/js/summernote-init.js
ideia_summernote/templates/ideia_summernote/default.html